trilateration/__init__.py
trilateration/test_trilateration.py
trilateration/trilateration.py
trilateration-1.0.dist-info/DESCRIPTION.rst
trilateration-1.0.dist-info/METADATA
trilateration-1.0.dist-info/RECORD
trilateration-1.0.dist-info/WHEEL
trilateration-1.0.dist-info/metadata.json
trilateration-1.0.dist-info/top_level.txt
