Metadata-Version: 2.0
Name: trilateration
Version: 1.0
Summary: Finding best intersection or its nearest point for 3 gateways and the distance traveled by the signal for TDOA/TOA trilateration
Home-page: https://github.com/robinroyer/trilateration
Author: Royer Robin
Author-email: ktyroby@hotmail.fr
License: UNKNOWN
Download-URL: https://github.com/robinroyer/trilateration/archive/0.1.tar.gz
Keywords: trilateration,toa,tdoa
Platform: UNKNOWN
